djoser/.codacy.yml
djoser/__init__.py
djoser/compat.py
djoser/conf.py
djoser/constants.py
djoser/email.py
djoser/permissions.py
djoser/serializers.py
djoser/signals.py
djoser/utils.py
djoser/views.py
djoser/locale/fr/LC_MESSAGES/django.po
djoser/locale/ka/LC_MESSAGES/django.po
djoser/locale/pl/LC_MESSAGES/django.po
djoser/locale/ru_RU/LC_MESSAGES/django.po
djoser/social/__init__.py
djoser/social/serializers.py
djoser/social/urls.py
djoser/social/views.py
djoser/social/backends/__init__.py
djoser/social/backends/facebook.py
djoser/social/token/__init__.py
djoser/social/token/jwt.py
djoser/templates/email/activation.html
djoser/templates/email/confirmation.html
djoser/templates/email/password_changed_confirmation.html
djoser/templates/email/password_reset.html
djoser/templates/email/username_changed_confirmation.html
djoser/templates/email/username_reset.html
djoser/urls/__init__.py
djoser/urls/authtoken.py
djoser/urls/base.py
djoser/urls/jwt.py
djoser_edge-2.0.4.dist-info/LICENSE
djoser_edge-2.0.4.dist-info/METADATA
djoser_edge-2.0.4.dist-info/WHEEL
djoser_edge-2.0.4.dist-info/top_level.txt
djoser_edge-2.0.4.dist-info/RECORD
