Metadata-Version: 2.1
Name: djoser-edge
Version: 2.0.4
Summary: REST version of Django authentication system.
Home-page: https://github.com/sunscrapers/djoser
Author: SUNSCRAPERS
Author-email: info@sunscrapers.com
License: MIT
Platform: UNKNOWN
Classifier: Development Status :: 5 - Production/Stable
Classifier: Framework :: Django
Classifier: Framework :: Django :: 2.2
Classifier: Intended Audience :: Developers
Classifier: License :: OSI Approved :: MIT License
Classifier: Operating System :: OS Independent
Classifier: Programming Language :: Python
Classifier: Programming Language :: Python :: 3.7
Classifier: Programming Language :: Python :: 3.8
Requires-Dist: django-templated-mail
Requires-Dist: drf-yasg-edge (>=2.0)
